yodalist/__init__.py
yodalist/yodalist.py
yodalist-0.1.22.dist-info/LICENSE
yodalist-0.1.22.dist-info/METADATA
yodalist-0.1.22.dist-info/WHEEL
yodalist-0.1.22.dist-info/top_level.txt
yodalist-0.1.22.dist-info/RECORD
