Metadata-Version: 2.1
Name: yodalist
Version: 0.1.22
Summary: For lists, yoda-indexing this package provides.
Home-page: https://gitlab.com/lynnpepin/yodalist
Author: lynn pepin
Author-email: 1914373-lynnpepin@users.noreply.gitlab.com
License: UNKNOWN
Project-URL: Bug Tracker, https://gitlab.com/lynnpepin/yodalist/-/issues
Platform: UNKNOWN
Classifier: Intended Audience :: Other Audience
Classifier: Programming Language :: Python :: 3
Classifier: License :: OSI Approved :: MIT License
Classifier: Operating System :: OS Independent
Requires-Python: >=3.6
License-File: LICENSE
